CCSVGit/Git.py
CCSVGit/Versioning.py
CCSVGit/__init__.py
CCSVGit-1.7.0.dist-info/LICENSE
CCSVGit-1.7.0.dist-info/METADATA
CCSVGit-1.7.0.dist-info/WHEEL
CCSVGit-1.7.0.dist-info/top_level.txt
CCSVGit-1.7.0.dist-info/RECORD
